CodeChat_Server/__init__.py
CodeChat_Server/__main__.py
CodeChat_Server/constants.py
CodeChat_Server/render_manager.py
CodeChat_Server/renderer.py
CodeChat_Server/server.py
CodeChat_Server/CodeChat_Client/static/CodeChat_client.css
CodeChat_Server/CodeChat_Client/static/CodeChat_client.js
CodeChat_Server/CodeChat_Client/static/ReconnectingWebsocket.js
CodeChat_Server/CodeChat_Client/static/splitter.css
CodeChat_Server/CodeChat_Client/static/splitter.js
CodeChat_Server/CodeChat_Client/templates/CodeChat_client.html
CodeChat_Server/CodeChat_Client/templates/insecure.html
CodeChat_Server/gen_py/__init__.py
CodeChat_Server/gen_py/CodeChat_Services/EditorPlugin.py
CodeChat_Server/gen_py/CodeChat_Services/__init__.py
CodeChat_Server/gen_py/CodeChat_Services/constants.py
CodeChat_Server/gen_py/CodeChat_Services/ttypes.py
CodeChat_Server/templates/doxygen/Doxyfile
CodeChat_Server/templates/doxygen/codechat_config.yaml
CodeChat_Server/templates/doxygen/main.c
CodeChat_Server/templates/javadoc/Simple.java
CodeChat_Server/templates/javadoc/codechat_config.yaml
CodeChat_Server/templates/mdbook/.gitignore
CodeChat_Server/templates/mdbook/book.toml
CodeChat_Server/templates/mdbook/codechat_config.yaml
CodeChat_Server/templates/mdbook/src/SUMMARY.md
CodeChat_Server/templates/mdbook/src/book.toml
CodeChat_Server/templates/mdbook/src/chapter_1.md
CodeChat_Server/templates/mdbook/src/chapter_2.py
CodeChat_Server/templates/mdbook/src/codechat-config.yaml
CodeChat_Server/templates/mkdocs/codechat_config.yaml
CodeChat_Server/templates/mkdocs/mkdocs.yml
CodeChat_Server/templates/mkdocs/docs/index.md
CodeChat_Server/templates/pretext/.gitignore
CodeChat_Server/templates/pretext/README.md
CodeChat_Server/templates/pretext/codechat_config.yaml
CodeChat_Server/templates/pretext/project.ptx
CodeChat_Server/templates/pretext/publication/publication.ptx
CodeChat_Server/templates/pretext/source/minimal.ptx
CodeChat_Server/templates/runestone/codechat_config.yaml
CodeChat_Server-0.2.25.dist-info/LICENSE.rst
CodeChat_Server-0.2.25.dist-info/METADATA
CodeChat_Server-0.2.25.dist-info/WHEEL
CodeChat_Server-0.2.25.dist-info/entry_points.txt
CodeChat_Server-0.2.25.dist-info/top_level.txt
CodeChat_Server-0.2.25.dist-info/RECORD
