Metadata-Version: 2.1
Name: CodeChat_Server
Version: 0.2.25
Summary: The CodeChat Server for software documentation
Home-page: http://codechat.readthedocs.io/en/latest/
Author: Bryan A. Jones
Author-email: bjones@ece.msstate.edu
License: GPLv3+
Keywords: literate programming
Classifier: Development Status :: 5 - Production/Stable
Classifier: Intended Audience :: Developers
Classifier: License :: OSI Approved :: GNU General Public License v3 or later (GPLv3+)
Classifier: Operating System :: OS Independent
Classifier: Natural Language :: English
Classifier: Programming Language :: Python :: 3
Classifier: Programming Language :: Python :: 3.7
Classifier: Programming Language :: Python :: 3.8
Classifier: Programming Language :: Python :: 3.9
Classifier: Programming Language :: Python :: 3.10
Classifier: Programming Language :: Python :: 3.11
Classifier: Topic :: Software Development :: Documentation
Classifier: Topic :: Text Processing :: Markup
Requires-Python: >=3.7
License-File: docs/LICENSE.rst
Requires-Dist: bottle
Requires-Dist: cherrypy
Requires-Dist: CodeChat
Requires-Dist: json-five
Requires-Dist: markdown
Requires-Dist: psutil
Requires-Dist: strictyaml
Requires-Dist: thrift
Requires-Dist: typer[all]
Requires-Dist: watchdog
Requires-Dist: websockets
Provides-Extra: test
Requires-Dist: black ; extra == 'test'
Requires-Dist: coverage ; extra == 'test'
Requires-Dist: flake8 ; extra == 'test'
Requires-Dist: myst-parser ; extra == 'test'
Requires-Dist: mypy ; extra == 'test'
Requires-Dist: pytest ; extra == 'test'
Requires-Dist: requests ; extra == 'test'
Requires-Dist: sphinx ; extra == 'test'
